LICENSE
MANIFEST.in
README.md
setup.py
test/__init__.py
test/test_convert.py
test/test_encode.py
test/test_extract.py
test/test_shingleset.py
treesimi/__init__.py
treesimi/convert.py
treesimi/encode.py
treesimi/extract.py
treesimi/shingleset.py
treesimi/utils_for_depparser.py
treesimi.egg-info/PKG-INFO
treesimi.egg-info/SOURCES.txt
treesimi.egg-info/dependency_links.txt
treesimi.egg-info/top_level.txt
treesimi.egg-info/zip-safe