Metadata-Version: 2.1
Name: treesimi
Version: 0.3.0
Summary: Compute similarity between netsted set based trees.
Home-page: http://github.com/ulf1/treesimi
Author: Ulf Hamster
Author-email: 554c46@gmail.com
License: Apache License 2.0
Platform: UNKNOWN
Requires-Python: >=3.6
License-File: LICENSE
